<?xml version="1.0" encoding="UTF-8"?>
<objects serializationModel="Studio.02.03.00">
	<object class="AudioFile" id="{ca44a76a-28e4-413b-9591-7bdd764b699b}">
		<property name="assetPath">
			<value>GruntsAndBarks/David_BulletHit/Trainwreck_RecSession-012.wav</value>
		</property>
		<property name="frequencyInKHz">
			<value>48</value>
		</property>
		<property name="channelCount">
			<value>1</value>
		</property>
		<property name="length">
			<value>0.29710416666666667</value>
		</property>
		<relationship name="masterAssetFolder">
			<destination>{0007398a-8526-4222-84a0-9fc057cc09e5}</destination>
		</relationship>
	</object>
</objects>
